{
    "minecraft:air": {
        "id": 0
    },
    "minecraft:stone": {
        "id": 1
    },
    "minecraft:granite": {
        "id": 2
    },
    "minecraft:polished_granite": {
        "id": 3
    },
    "minecraft:diorite": {
        "id": 4
    },
    "minecraft:polished_diorite": {
        "id": 5
    },
    "minecraft:andesite": {
        "id": 6
    },
    "minecraft:polished_andesite": {
        "id": 7
    },
    "minecraft:deepslate": {
        "id": 8
    },
    "minecraft:cobbled_deepslate": {
        "id": 9
    },
    "minecraft:polished_deepslate": {
        "id": 10
    },
    "minecraft:calcite": {
        "id": 11
    },
    "minecraft:tuff": {
        "id": 12
    },
    "minecraft:dripstone_block": {
        "id": 13
    },
    "minecraft:grass_block": {
        "id": 14
    },
    "minecraft:dirt": {
        "id": 15
    },
    "minecraft:coarse_dirt": {
        "id": 16
    },
    "minecraft:podzol": {
        "id": 17
    },
    "minecraft:rooted_dirt": {
        "id": 18
    },
    "minecraft:crimson_nylium": {
        "id": 19
    },
    "minecraft:warped_nylium": {
        "id": 20
    },
    "minecraft:cobblestone": {
        "id": 21
    },
    "minecraft:oak_planks": {
        "id": 22
    },
    "minecraft:spruce_planks": {
        "id": 23
    },
    "minecraft:birch_planks": {
        "id": 24
    },
    "minecraft:jungle_planks": {
        "id": 25
    },
    "minecraft:acacia_planks": {
        "id": 26
    },
    "minecraft:dark_oak_planks": {
        "id": 27
    },
    "minecraft:crimson_planks": {
        "id": 28
    },
    "minecraft:warped_planks": {
        "id": 29
    },
    "minecraft:oak_sapling": {
        "id": 30
    },
    "minecraft:spruce_sapling": {
        "id": 31
    },
    "minecraft:birch_sapling": {
        "id": 32
    },
    "minecraft:jungle_sapling": {
        "id": 33
    },
    "minecraft:acacia_sapling": {
        "id": 34
    },
    "minecraft:dark_oak_sapling": {
        "id": 35
    },
    "minecraft:bedrock": {
        "id": 36
    },
    "minecraft:sand": {
        "id": 37
    },
    "minecraft:red_sand": {
        "id": 38
    },
    "minecraft:gravel": {
        "id": 39
    },
    "minecraft:coal_ore": {
        "id": 40
    },
    "minecraft:deepslate_coal_ore": {
        "id": 41
    },
    "minecraft:iron_ore": {
        "id": 42
    },
    "minecraft:deepslate_iron_ore": {
        "id": 43
    },
    "minecraft:copper_ore": {
        "id": 44
    },
    "minecraft:deepslate_copper_ore": {
        "id": 45
    },
    "minecraft:gold_ore": {
        "id": 46
    },
    "minecraft:deepslate_gold_ore": {
        "id": 47
    },
    "minecraft:redstone_ore": {
        "id": 48
    },
    "minecraft:deepslate_redstone_ore": {
        "id": 49
    },
    "minecraft:emerald_ore": {
        "id": 50
    },
    "minecraft:deepslate_emerald_ore": {
        "id": 51
    },
    "minecraft:lapis_ore": {
        "id": 52
    },
    "minecraft:deepslate_lapis_ore": {
        "id": 53
    },
    "minecraft:diamond_ore": {
        "id": 54
    },
    "minecraft:deepslate_diamond_ore": {
        "id": 55
    },
    "minecraft:nether_gold_ore": {
        "id": 56
    },
    "minecraft:nether_quartz_ore": {
        "id": 57
    },
    "minecraft:ancient_debris": {
        "id": 58
    },
    "minecraft:coal_block": {
        "id": 59
    },
    "minecraft:raw_iron_block": {
        "id": 60
    },
    "minecraft:raw_copper_block": {
        "id": 61
    },
    "minecraft:raw_gold_block": {
        "id": 62
    },
    "minecraft:amethyst_block": {
        "id": 63
    },
    "minecraft:budding_amethyst": {
        "id": 64
    },
    "minecraft:iron_block": {
        "id": 65
    },
    "minecraft:copper_block": {
        "id": 66
    },
    "minecraft:gold_block": {
        "id": 67
    },
    "minecraft:diamond_block": {
        "id": 68
    },
    "minecraft:netherite_block": {
        "id": 69
    },
    "minecraft:exposed_copper": {
        "id": 70
    },
    "minecraft:weathered_copper": {
        "id": 71
    },
    "minecraft:oxidized_copper": {
        "id": 72
    },
    "minecraft:cut_copper": {
        "id": 73
    },
    "minecraft:exposed_cut_copper": {
        "id": 74
    },
    "minecraft:weathered_cut_copper": {
        "id": 75
    },
    "minecraft:oxidized_cut_copper": {
        "id": 76
    },
    "minecraft:cut_copper_stairs": {
        "id": 77
    },
    "minecraft:exposed_cut_copper_stairs": {
        "id": 78
    },
    "minecraft:weathered_cut_copper_stairs": {
        "id": 79
    },
    "minecraft:oxidized_cut_copper_stairs": {
        "id": 80
    },
    "minecraft:cut_copper_slab": {
        "id": 81
    },
    "minecraft:exposed_cut_copper_slab": {
        "id": 82
    },
    "minecraft:weathered_cut_copper_slab": {
        "id": 83
    },
    "minecraft:oxidized_cut_copper_slab": {
        "id": 84
    },
    "minecraft:waxed_copper_block": {
        "id": 85
    },
    "minecraft:waxed_exposed_copper": {
        "id": 86
    },
    "minecraft:waxed_weathered_copper": {
        "id": 87
    },
    "minecraft:waxed_oxidized_copper": {
        "id": 88
    },
    "minecraft:waxed_cut_copper": {
        "id": 89
    },
    "minecraft:waxed_exposed_cut_copper": {
        "id": 90
    },
    "minecraft:waxed_weathered_cut_copper": {
        "id": 91
    },
    "minecraft:waxed_oxidized_cut_copper": {
        "id": 92
    },
    "minecraft:waxed_cut_copper_stairs": {
        "id": 93
    },
    "minecraft:waxed_exposed_cut_copper_stairs": {
        "id": 94
    },
    "minecraft:waxed_weathered_cut_copper_stairs": {
        "id": 95
    },
    "minecraft:waxed_oxidized_cut_copper_stairs": {
        "id": 96
    },
    "minecraft:waxed_cut_copper_slab": {
        "id": 97
    },
    "minecraft:waxed_exposed_cut_copper_slab": {
        "id": 98
    },
    "minecraft:waxed_weathered_cut_copper_slab": {
        "id": 99
    },
    "minecraft:waxed_oxidized_cut_copper_slab": {
        "id": 100
    },
    "minecraft:oak_log": {
        "id": 101
    },
    "minecraft:spruce_log": {
        "id": 102
    },
    "minecraft:birch_log": {
        "id": 103
    },
    "minecraft:jungle_log": {
        "id": 104
    },
    "minecraft:acacia_log": {
        "id": 105
    },
    "minecraft:dark_oak_log": {
        "id": 106
    },
    "minecraft:crimson_stem": {
        "id": 107
    },
    "minecraft:warped_stem": {
        "id": 108
    },
    "minecraft:stripped_oak_log": {
        "id": 109
    },
    "minecraft:stripped_spruce_log": {
        "id": 110
    },
    "minecraft:stripped_birch_log": {
        "id": 111
    },
    "minecraft:stripped_jungle_log": {
        "id": 112
    },
    "minecraft:stripped_acacia_log": {
        "id": 113
    },
    "minecraft:stripped_dark_oak_log": {
        "id": 114
    },
    "minecraft:stripped_crimson_stem": {
        "id": 115
    },
    "minecraft:stripped_warped_stem": {
        "id": 116
    },
    "minecraft:stripped_oak_wood": {
        "id": 117
    },
    "minecraft:stripped_spruce_wood": {
        "id": 118
    },
    "minecraft:stripped_birch_wood": {
        "id": 119
    },
    "minecraft:stripped_jungle_wood": {
        "id": 120
    },
    "minecraft:stripped_acacia_wood": {
        "id": 121
    },
    "minecraft:stripped_dark_oak_wood": {
        "id": 122
    },
    "minecraft:stripped_crimson_hyphae": {
        "id": 123
    },
    "minecraft:stripped_warped_hyphae": {
        "id": 124
    },
    "minecraft:oak_wood": {
        "id": 125
    },
    "minecraft:spruce_wood": {
        "id": 126
    },
    "minecraft:birch_wood": {
        "id": 127
    },
    "minecraft:jungle_wood": {
        "id": 128
    },
    "minecraft:acacia_wood": {
        "id": 129
    },
    "minecraft:dark_oak_wood": {
        "id": 130
    },
    "minecraft:crimson_hyphae": {
        "id": 131
    },
    "minecraft:warped_hyphae": {
        "id": 132
    },
    "minecraft:oak_leaves": {
        "id": 133
    },
    "minecraft:spruce_leaves": {
        "id": 134
    },
    "minecraft:birch_leaves": {
        "id": 135
    },
    "minecraft:jungle_leaves": {
        "id": 136
    },
    "minecraft:acacia_leaves": {
        "id": 137
    },
    "minecraft:dark_oak_leaves": {
        "id": 138
    },
    "minecraft:azalea_leaves": {
        "id": 139
    },
    "minecraft:flowering_azalea_leaves": {
        "id": 140
    },
    "minecraft:sponge": {
        "id": 141
    },
    "minecraft:wet_sponge": {
        "id": 142
    },
    "minecraft:glass": {
        "id": 143
    },
    "minecraft:tinted_glass": {
        "id": 144
    },
    "minecraft:lapis_block": {
        "id": 145
    },
    "minecraft:sandstone": {
        "id": 146
    },
    "minecraft:chiseled_sandstone": {
        "id": 147
    },
    "minecraft:cut_sandstone": {
        "id": 148
    },
    "minecraft:cobweb": {
        "id": 149
    },
    "minecraft:grass": {
        "id": 150
    },
    "minecraft:fern": {
        "id": 151
    },
    "minecraft:azalea": {
        "id": 152
    },
    "minecraft:flowering_azalea": {
        "id": 153
    },
    "minecraft:dead_bush": {
        "id": 154
    },
    "minecraft:seagrass": {
        "id": 155
    },
    "minecraft:sea_pickle": {
        "id": 156
    },
    "minecraft:white_wool": {
        "id": 157
    },
    "minecraft:orange_wool": {
        "id": 158
    },
    "minecraft:magenta_wool": {
        "id": 159
    },
    "minecraft:light_blue_wool": {
        "id": 160
    },
    "minecraft:yellow_wool": {
        "id": 161
    },
    "minecraft:lime_wool": {
        "id": 162
    },
    "minecraft:pink_wool": {
        "id": 163
    },
    "minecraft:gray_wool": {
        "id": 164
    },
    "minecraft:light_gray_wool": {
        "id": 165
    },
    "minecraft:cyan_wool": {
        "id": 166
    },
    "minecraft:purple_wool": {
        "id": 167
    },
    "minecraft:blue_wool": {
        "id": 168
    },
    "minecraft:brown_wool": {
        "id": 169
    },
    "minecraft:green_wool": {
        "id": 170
    },
    "minecraft:red_wool": {
        "id": 171
    },
    "minecraft:black_wool": {
        "id": 172
    },
    "minecraft:dandelion": {
        "id": 173
    },
    "minecraft:poppy": {
        "id": 174
    },
    "minecraft:blue_orchid": {
        "id": 175
    },
    "minecraft:allium": {
        "id": 176
    },
    "minecraft:azure_bluet": {
        "id": 177
    },
    "minecraft:red_tulip": {
        "id": 178
    },
    "minecraft:orange_tulip": {
        "id": 179
    },
    "minecraft:white_tulip": {
        "id": 180
    },
    "minecraft:pink_tulip": {
        "id": 181
    },
    "minecraft:oxeye_daisy": {
        "id": 182
    },
    "minecraft:cornflower": {
        "id": 183
    },
    "minecraft:lily_of_the_valley": {
        "id": 184
    },
    "minecraft:wither_rose": {
        "id": 185
    },
    "minecraft:spore_blossom": {
        "id": 186
    },
    "minecraft:brown_mushroom": {
        "id": 187
    },
    "minecraft:red_mushroom": {
        "id": 188
    },
    "minecraft:crimson_fungus": {
        "id": 189
    },
    "minecraft:warped_fungus": {
        "id": 190
    },
    "minecraft:crimson_roots": {
        "id": 191
    },
    "minecraft:warped_roots": {
        "id": 192
    },
    "minecraft:nether_sprouts": {
        "id": 193
    },
    "minecraft:weeping_vines": {
        "id": 194
    },
    "minecraft:twisting_vines": {
        "id": 195
    },
    "minecraft:sugar_cane": {
        "id": 196
    },
    "minecraft:kelp": {
        "id": 197
    },
    "minecraft:moss_carpet": {
        "id": 198
    },
    "minecraft:moss_block": {
        "id": 199
    },
    "minecraft:hanging_roots": {
        "id": 200
    },
    "minecraft:big_dripleaf": {
        "id": 201
    },
    "minecraft:small_dripleaf": {
        "id": 202
    },
    "minecraft:bamboo": {
        "id": 203
    },
    "minecraft:oak_slab": {
        "id": 204
    },
    "minecraft:spruce_slab": {
        "id": 205
    },
    "minecraft:birch_slab": {
        "id": 206
    },
    "minecraft:jungle_slab": {
        "id": 207
    },
    "minecraft:acacia_slab": {
        "id": 208
    },
    "minecraft:dark_oak_slab": {
        "id": 209
    },
    "minecraft:crimson_slab": {
        "id": 210
    },
    "minecraft:warped_slab": {
        "id": 211
    },
    "minecraft:stone_slab": {
        "id": 212
    },
    "minecraft:smooth_stone_slab": {
        "id": 213
    },
    "minecraft:sandstone_slab": {
        "id": 214
    },
    "minecraft:cut_sandstone_slab": {
        "id": 215
    },
    "minecraft:petrified_oak_slab": {
        "id": 216
    },
    "minecraft:cobblestone_slab": {
        "id": 217
    },
    "minecraft:brick_slab": {
        "id": 218
    },
    "minecraft:stone_brick_slab": {
        "id": 219
    },
    "minecraft:nether_brick_slab": {
        "id": 220
    },
    "minecraft:quartz_slab": {
        "id": 221
    },
    "minecraft:red_sandstone_slab": {
        "id": 222
    },
    "minecraft:cut_red_sandstone_slab": {
        "id": 223
    },
    "minecraft:purpur_slab": {
        "id": 224
    },
    "minecraft:prismarine_slab": {
        "id": 225
    },
    "minecraft:prismarine_brick_slab": {
        "id": 226
    },
    "minecraft:dark_prismarine_slab": {
        "id": 227
    },
    "minecraft:smooth_quartz": {
        "id": 228
    },
    "minecraft:smooth_red_sandstone": {
        "id": 229
    },
    "minecraft:smooth_sandstone": {
        "id": 230
    },
    "minecraft:smooth_stone": {
        "id": 231
    },
    "minecraft:bricks": {
        "id": 232
    },
    "minecraft:bookshelf": {
        "id": 233
    },
    "minecraft:mossy_cobblestone": {
        "id": 234
    },
    "minecraft:obsidian": {
        "id": 235
    },
    "minecraft:torch": {
        "id": 236
    },
    "minecraft:end_rod": {
        "id": 237
    },
    "minecraft:chorus_plant": {
        "id": 238
    },
    "minecraft:chorus_flower": {
        "id": 239
    },
    "minecraft:purpur_block": {
        "id": 240
    },
    "minecraft:purpur_pillar": {
        "id": 241
    },
    "minecraft:purpur_stairs": {
        "id": 242
    },
    "minecraft:spawner": {
        "id": 243
    },
    "minecraft:oak_stairs": {
        "id": 244
    },
    "minecraft:chest": {
        "id": 245
    },
    "minecraft:crafting_table": {
        "id": 246
    },
    "minecraft:farmland": {
        "id": 247
    },
    "minecraft:furnace": {
        "id": 248
    },
    "minecraft:ladder": {
        "id": 249
    },
    "minecraft:cobblestone_stairs": {
        "id": 250
    },
    "minecraft:snow": {
        "id": 251
    },
    "minecraft:ice": {
        "id": 252
    },
    "minecraft:snow_block": {
        "id": 253
    },
    "minecraft:cactus": {
        "id": 254
    },
    "minecraft:clay": {
        "id": 255
    },
    "minecraft:jukebox": {
        "id": 256
    },
    "minecraft:oak_fence": {
        "id": 257
    },
    "minecraft:spruce_fence": {
        "id": 258
    },
    "minecraft:birch_fence": {
        "id": 259
    },
    "minecraft:jungle_fence": {
        "id": 260
    },
    "minecraft:acacia_fence": {
        "id": 261
    },
    "minecraft:dark_oak_fence": {
        "id": 262
    },
    "minecraft:crimson_fence": {
        "id": 263
    },
    "minecraft:warped_fence": {
        "id": 264
    },
    "minecraft:pumpkin": {
        "id": 265
    },
    "minecraft:carved_pumpkin": {
        "id": 266
    },
    "minecraft:jack_o_lantern": {
        "id": 267
    },
    "minecraft:netherrack": {
        "id": 268
    },
    "minecraft:soul_sand": {
        "id": 269
    },
    "minecraft:soul_soil": {
        "id": 270
    },
    "minecraft:basalt": {
        "id": 271
    },
    "minecraft:polished_basalt": {
        "id": 272
    },
    "minecraft:smooth_basalt": {
        "id": 273
    },
    "minecraft:soul_torch": {
        "id": 274
    },
    "minecraft:glowstone": {
        "id": 275
    },
    "minecraft:infested_stone": {
        "id": 276
    },
    "minecraft:infested_cobblestone": {
        "id": 277
    },
    "minecraft:infested_stone_bricks": {
        "id": 278
    },
    "minecraft:infested_mossy_stone_bricks": {
        "id": 279
    },
    "minecraft:infested_cracked_stone_bricks": {
        "id": 280
    },
    "minecraft:infested_chiseled_stone_bricks": {
        "id": 281
    },
    "minecraft:infested_deepslate": {
        "id": 282
    },
    "minecraft:stone_bricks": {
        "id": 283
    },
    "minecraft:mossy_stone_bricks": {
        "id": 284
    },
    "minecraft:cracked_stone_bricks": {
        "id": 285
    },
    "minecraft:chiseled_stone_bricks": {
        "id": 286
    },
    "minecraft:deepslate_bricks": {
        "id": 287
    },
    "minecraft:cracked_deepslate_bricks": {
        "id": 288
    },
    "minecraft:deepslate_tiles": {
        "id": 289
    },
    "minecraft:cracked_deepslate_tiles": {
        "id": 290
    },
    "minecraft:chiseled_deepslate": {
        "id": 291
    },
    "minecraft:brown_mushroom_block": {
        "id": 292
    },
    "minecraft:red_mushroom_block": {
        "id": 293
    },
    "minecraft:mushroom_stem": {
        "id": 294
    },
    "minecraft:iron_bars": {
        "id": 295
    },
    "minecraft:chain": {
        "id": 296
    },
    "minecraft:glass_pane": {
        "id": 297
    },
    "minecraft:melon": {
        "id": 298
    },
    "minecraft:vine": {
        "id": 299
    },
    "minecraft:glow_lichen": {
        "id": 300
    },
    "minecraft:brick_stairs": {
        "id": 301
    },
    "minecraft:stone_brick_stairs": {
        "id": 302
    },
    "minecraft:mycelium": {
        "id": 303
    },
    "minecraft:lily_pad": {
        "id": 304
    },
    "minecraft:nether_bricks": {
        "id": 305
    },
    "minecraft:cracked_nether_bricks": {
        "id": 306
    },
    "minecraft:chiseled_nether_bricks": {
        "id": 307
    },
    "minecraft:nether_brick_fence": {
        "id": 308
    },
    "minecraft:nether_brick_stairs": {
        "id": 309
    },
    "minecraft:enchanting_table": {
        "id": 310
    },
    "minecraft:end_portal_frame": {
        "id": 311
    },
    "minecraft:end_stone": {
        "id": 312
    },
    "minecraft:end_stone_bricks": {
        "id": 313
    },
    "minecraft:dragon_egg": {
        "id": 314
    },
    "minecraft:sandstone_stairs": {
        "id": 315
    },
    "minecraft:ender_chest": {
        "id": 316
    },
    "minecraft:emerald_block": {
        "id": 317
    },
    "minecraft:spruce_stairs": {
        "id": 318
    },
    "minecraft:birch_stairs": {
        "id": 319
    },
    "minecraft:jungle_stairs": {
        "id": 320
    },
    "minecraft:crimson_stairs": {
        "id": 321
    },
    "minecraft:warped_stairs": {
        "id": 322
    },
    "minecraft:command_block": {
        "id": 323
    },
    "minecraft:beacon": {
        "id": 324
    },
    "minecraft:cobblestone_wall": {
        "id": 325
    },
    "minecraft:mossy_cobblestone_wall": {
        "id": 326
    },
    "minecraft:brick_wall": {
        "id": 327
    },
    "minecraft:prismarine_wall": {
        "id": 328
    },
    "minecraft:red_sandstone_wall": {
        "id": 329
    },
    "minecraft:mossy_stone_brick_wall": {
        "id": 330
    },
    "minecraft:granite_wall": {
        "id": 331
    },
    "minecraft:stone_brick_wall": {
        "id": 332
    },
    "minecraft:nether_brick_wall": {
        "id": 333
    },
    "minecraft:andesite_wall": {
        "id": 334
    },
    "minecraft:red_nether_brick_wall": {
        "id": 335
    },
    "minecraft:sandstone_wall": {
        "id": 336
    },
    "minecraft:end_stone_brick_wall": {
        "id": 337
    },
    "minecraft:diorite_wall": {
        "id": 338
    },
    "minecraft:blackstone_wall": {
        "id": 339
    },
    "minecraft:polished_blackstone_wall": {
        "id": 340
    },
    "minecraft:polished_blackstone_brick_wall": {
        "id": 341
    },
    "minecraft:cobbled_deepslate_wall": {
        "id": 342
    },
    "minecraft:polished_deepslate_wall": {
        "id": 343
    },
    "minecraft:deepslate_brick_wall": {
        "id": 344
    },
    "minecraft:deepslate_tile_wall": {
        "id": 345
    },
    "minecraft:anvil": {
        "id": 346
    },
    "minecraft:chipped_anvil": {
        "id": 347
    },
    "minecraft:damaged_anvil": {
        "id": 348
    },
    "minecraft:chiseled_quartz_block": {
        "id": 349
    },
    "minecraft:quartz_block": {
        "id": 350
    },
    "minecraft:quartz_bricks": {
        "id": 351
    },
    "minecraft:quartz_pillar": {
        "id": 352
    },
    "minecraft:quartz_stairs": {
        "id": 353
    },
    "minecraft:white_terracotta": {
        "id": 354
    },
    "minecraft:orange_terracotta": {
        "id": 355
    },
    "minecraft:magenta_terracotta": {
        "id": 356
    },
    "minecraft:light_blue_terracotta": {
        "id": 357
    },
    "minecraft:yellow_terracotta": {
        "id": 358
    },
    "minecraft:lime_terracotta": {
        "id": 359
    },
    "minecraft:pink_terracotta": {
        "id": 360
    },
    "minecraft:gray_terracotta": {
        "id": 361
    },
    "minecraft:light_gray_terracotta": {
        "id": 362
    },
    "minecraft:cyan_terracotta": {
        "id": 363
    },
    "minecraft:purple_terracotta": {
        "id": 364
    },
    "minecraft:blue_terracotta": {
        "id": 365
    },
    "minecraft:brown_terracotta": {
        "id": 366
    },
    "minecraft:green_terracotta": {
        "id": 367
    },
    "minecraft:red_terracotta": {
        "id": 368
    },
    "minecraft:black_terracotta": {
        "id": 369
    },
    "minecraft:barrier": {
        "id": 370
    },
    "minecraft:light": {
        "id": 371
    },
    "minecraft:hay_block": {
        "id": 372
    },
    "minecraft:white_carpet": {
        "id": 373
    },
    "minecraft:orange_carpet": {
        "id": 374
    },
    "minecraft:magenta_carpet": {
        "id": 375
    },
    "minecraft:light_blue_carpet": {
        "id": 376
    },
    "minecraft:yellow_carpet": {
        "id": 377
    },
    "minecraft:lime_carpet": {
        "id": 378
    },
    "minecraft:pink_carpet": {
        "id": 379
    },
    "minecraft:gray_carpet": {
        "id": 380
    },
    "minecraft:light_gray_carpet": {
        "id": 381
    },
    "minecraft:cyan_carpet": {
        "id": 382
    },
    "minecraft:purple_carpet": {
        "id": 383
    },
    "minecraft:blue_carpet": {
        "id": 384
    },
    "minecraft:brown_carpet": {
        "id": 385
    },
    "minecraft:green_carpet": {
        "id": 386
    },
    "minecraft:red_carpet": {
        "id": 387
    },
    "minecraft:black_carpet": {
        "id": 388
    },
    "minecraft:terracotta": {
        "id": 389
    },
    "minecraft:packed_ice": {
        "id": 390
    },
    "minecraft:acacia_stairs": {
        "id": 391
    },
    "minecraft:dark_oak_stairs": {
        "id": 392
    },
    "minecraft:dirt_path": {
        "id": 393
    },
    "minecraft:sunflower": {
        "id": 394
    },
    "minecraft:lilac": {
        "id": 395
    },
    "minecraft:rose_bush": {
        "id": 396
    },
    "minecraft:peony": {
        "id": 397
    },
    "minecraft:tall_grass": {
        "id": 398
    },
    "minecraft:large_fern": {
        "id": 399
    },
    "minecraft:white_stained_glass": {
        "id": 400
    },
    "minecraft:orange_stained_glass": {
        "id": 401
    },
    "minecraft:magenta_stained_glass": {
        "id": 402
    },
    "minecraft:light_blue_stained_glass": {
        "id": 403
    },
    "minecraft:yellow_stained_glass": {
        "id": 404
    },
    "minecraft:lime_stained_glass": {
        "id": 405
    },
    "minecraft:pink_stained_glass": {
        "id": 406
    },
    "minecraft:gray_stained_glass": {
        "id": 407
    },
    "minecraft:light_gray_stained_glass": {
        "id": 408
    },
    "minecraft:cyan_stained_glass": {
        "id": 409
    },
    "minecraft:purple_stained_glass": {
        "id": 410
    },
    "minecraft:blue_stained_glass": {
        "id": 411
    },
    "minecraft:brown_stained_glass": {
        "id": 412
    },
    "minecraft:green_stained_glass": {
        "id": 413
    },
    "minecraft:red_stained_glass": {
        "id": 414
    },
    "minecraft:black_stained_glass": {
        "id": 415
    },
    "minecraft:white_stained_glass_pane": {
        "id": 416
    },
    "minecraft:orange_stained_glass_pane": {
        "id": 417
    },
    "minecraft:magenta_stained_glass_pane": {
        "id": 418
    },
    "minecraft:light_blue_stained_glass_pane": {
        "id": 419
    },
    "minecraft:yellow_stained_glass_pane": {
        "id": 420
    },
    "minecraft:lime_stained_glass_pane": {
        "id": 421
    },
    "minecraft:pink_stained_glass_pane": {
        "id": 422
    },
    "minecraft:gray_stained_glass_pane": {
        "id": 423
    },
    "minecraft:light_gray_stained_glass_pane": {
        "id": 424
    },
    "minecraft:cyan_stained_glass_pane": {
        "id": 425
    },
    "minecraft:purple_stained_glass_pane": {
        "id": 426
    },
    "minecraft:blue_stained_glass_pane": {
        "id": 427
    },
    "minecraft:brown_stained_glass_pane": {
        "id": 428
    },
    "minecraft:green_stained_glass_pane": {
        "id": 429
    },
    "minecraft:red_stained_glass_pane": {
        "id": 430
    },
    "minecraft:black_stained_glass_pane": {
        "id": 431
    },
    "minecraft:prismarine": {
        "id": 432
    },
    "minecraft:prismarine_bricks": {
        "id": 433
    },
    "minecraft:dark_prismarine": {
        "id": 434
    },
    "minecraft:prismarine_stairs": {
        "id": 435
    },
    "minecraft:prismarine_brick_stairs": {
        "id": 436
    },
    "minecraft:dark_prismarine_stairs": {
        "id": 437
    },
    "minecraft:sea_lantern": {
        "id": 438
    },
    "minecraft:red_sandstone": {
        "id": 439
    },
    "minecraft:chiseled_red_sandstone": {
        "id": 440
    },
    "minecraft:cut_red_sandstone": {
        "id": 441
    },
    "minecraft:red_sandstone_stairs": {
        "id": 442
    },
    "minecraft:repeating_command_block": {
        "id": 443
    },
    "minecraft:chain_command_block": {
        "id": 444
    },
    "minecraft:magma_block": {
        "id": 445
    },
    "minecraft:nether_wart_block": {
        "id": 446
    },
    "minecraft:warped_wart_block": {
        "id": 447
    },
    "minecraft:red_nether_bricks": {
        "id": 448
    },
    "minecraft:bone_block": {
        "id": 449
    },
    "minecraft:structure_void": {
        "id": 450
    },
    "minecraft:shulker_box": {
        "id": 451,
        "stack_size": 1
    },
    "minecraft:white_shulker_box": {
        "id": 452,
        "stack_size": 1
    },
    "minecraft:orange_shulker_box": {
        "id": 453,
        "stack_size": 1
    },
    "minecraft:magenta_shulker_box": {
        "id": 454,
        "stack_size": 1
    },
    "minecraft:light_blue_shulker_box": {
        "id": 455,
        "stack_size": 1
    },
    "minecraft:yellow_shulker_box": {
        "id": 456,
        "stack_size": 1
    },
    "minecraft:lime_shulker_box": {
        "id": 457,
        "stack_size": 1
    },
    "minecraft:pink_shulker_box": {
        "id": 458,
        "stack_size": 1
    },
    "minecraft:gray_shulker_box": {
        "id": 459,
        "stack_size": 1
    },
    "minecraft:light_gray_shulker_box": {
        "id": 460,
        "stack_size": 1
    },
    "minecraft:cyan_shulker_box": {
        "id": 461,
        "stack_size": 1
    },
    "minecraft:purple_shulker_box": {
        "id": 462,
        "stack_size": 1
    },
    "minecraft:blue_shulker_box": {
        "id": 463,
        "stack_size": 1
    },
    "minecraft:brown_shulker_box": {
        "id": 464,
        "stack_size": 1
    },
    "minecraft:green_shulker_box": {
        "id": 465,
        "stack_size": 1
    },
    "minecraft:red_shulker_box": {
        "id": 466,
        "stack_size": 1
    },
    "minecraft:black_shulker_box": {
        "id": 467,
        "stack_size": 1
    },
    "minecraft:white_glazed_terracotta": {
        "id": 468
    },
    "minecraft:orange_glazed_terracotta": {
        "id": 469
    },
    "minecraft:magenta_glazed_terracotta": {
        "id": 470
    },
    "minecraft:light_blue_glazed_terracotta": {
        "id": 471
    },
    "minecraft:yellow_glazed_terracotta": {
        "id": 472
    },
    "minecraft:lime_glazed_terracotta": {
        "id": 473
    },
    "minecraft:pink_glazed_terracotta": {
        "id": 474
    },
    "minecraft:gray_glazed_terracotta": {
        "id": 475
    },
    "minecraft:light_gray_glazed_terracotta": {
        "id": 476
    },
    "minecraft:cyan_glazed_terracotta": {
        "id": 477
    },
    "minecraft:purple_glazed_terracotta": {
        "id": 478
    },
    "minecraft:blue_glazed_terracotta": {
        "id": 479
    },
    "minecraft:brown_glazed_terracotta": {
        "id": 480
    },
    "minecraft:green_glazed_terracotta": {
        "id": 481
    },
    "minecraft:red_glazed_terracotta": {
        "id": 482
    },
    "minecraft:black_glazed_terracotta": {
        "id": 483
    },
    "minecraft:white_concrete": {
        "id": 484
    },
    "minecraft:orange_concrete": {
        "id": 485
    },
    "minecraft:magenta_concrete": {
        "id": 486
    },
    "minecraft:light_blue_concrete": {
        "id": 487
    },
    "minecraft:yellow_concrete": {
        "id": 488
    },
    "minecraft:lime_concrete": {
        "id": 489
    },
    "minecraft:pink_concrete": {
        "id": 490
    },
    "minecraft:gray_concrete": {
        "id": 491
    },
    "minecraft:light_gray_concrete": {
        "id": 492
    },
    "minecraft:cyan_concrete": {
        "id": 493
    },
    "minecraft:purple_concrete": {
        "id": 494
    },
    "minecraft:blue_concrete": {
        "id": 495
    },
    "minecraft:brown_concrete": {
        "id": 496
    },
    "minecraft:green_concrete": {
        "id": 497
    },
    "minecraft:red_concrete": {
        "id": 498
    },
    "minecraft:black_concrete": {
        "id": 499
    },
    "minecraft:white_concrete_powder": {
        "id": 500
    },
    "minecraft:orange_concrete_powder": {
        "id": 501
    },
    "minecraft:magenta_concrete_powder": {
        "id": 502
    },
    "minecraft:light_blue_concrete_powder": {
        "id": 503
    },
    "minecraft:yellow_concrete_powder": {
        "id": 504
    },
    "minecraft:lime_concrete_powder": {
        "id": 505
    },
    "minecraft:pink_concrete_powder": {
        "id": 506
    },
    "minecraft:gray_concrete_powder": {
        "id": 507
    },
    "minecraft:light_gray_concrete_powder": {
        "id": 508
    },
    "minecraft:cyan_concrete_powder": {
        "id": 509
    },
    "minecraft:purple_concrete_powder": {
        "id": 510
    },
    "minecraft:blue_concrete_powder": {
        "id": 511
    },
    "minecraft:brown_concrete_powder": {
        "id": 512
    },
    "minecraft:green_concrete_powder": {
        "id": 513
    },
    "minecraft:red_concrete_powder": {
        "id": 514
    },
    "minecraft:black_concrete_powder": {
        "id": 515
    },
    "minecraft:turtle_egg": {
        "id": 516
    },
    "minecraft:dead_tube_coral_block": {
        "id": 517
    },
    "minecraft:dead_brain_coral_block": {
        "id": 518
    },
    "minecraft:dead_bubble_coral_block": {
        "id": 519
    },
    "minecraft:dead_fire_coral_block": {
        "id": 520
    },
    "minecraft:dead_horn_coral_block": {
        "id": 521
    },
    "minecraft:tube_coral_block": {
        "id": 522
    },
    "minecraft:brain_coral_block": {
        "id": 523
    },
    "minecraft:bubble_coral_block": {
        "id": 524
    },
    "minecraft:fire_coral_block": {
        "id": 525
    },
    "minecraft:horn_coral_block": {
        "id": 526
    },
    "minecraft:tube_coral": {
        "id": 527
    },
    "minecraft:brain_coral": {
        "id": 528
    },
    "minecraft:bubble_coral": {
        "id": 529
    },
    "minecraft:fire_coral": {
        "id": 530
    },
    "minecraft:horn_coral": {
        "id": 531
    },
    "minecraft:dead_brain_coral": {
        "id": 532
    },
    "minecraft:dead_bubble_coral": {
        "id": 533
    },
    "minecraft:dead_fire_coral": {
        "id": 534
    },
    "minecraft:dead_horn_coral": {
        "id": 535
    },
    "minecraft:dead_tube_coral": {
        "id": 536
    },
    "minecraft:tube_coral_fan": {
        "id": 537
    },
    "minecraft:brain_coral_fan": {
        "id": 538
    },
    "minecraft:bubble_coral_fan": {
        "id": 539
    },
    "minecraft:fire_coral_fan": {
        "id": 540
    },
    "minecraft:horn_coral_fan": {
        "id": 541
    },
    "minecraft:dead_tube_coral_fan": {
        "id": 542
    },
    "minecraft:dead_brain_coral_fan": {
        "id": 543
    },
    "minecraft:dead_bubble_coral_fan": {
        "id": 544
    },
    "minecraft:dead_fire_coral_fan": {
        "id": 545
    },
    "minecraft:dead_horn_coral_fan": {
        "id": 546
    },
    "minecraft:blue_ice": {
        "id": 547
    },
    "minecraft:conduit": {
        "id": 548
    },
    "minecraft:polished_granite_stairs": {
        "id": 549
    },
    "minecraft:smooth_red_sandstone_stairs": {
        "id": 550
    },
    "minecraft:mossy_stone_brick_stairs": {
        "id": 551
    },
    "minecraft:polished_diorite_stairs": {
        "id": 552
    },
    "minecraft:mossy_cobblestone_stairs": {
        "id": 553
    },
    "minecraft:end_stone_brick_stairs": {
        "id": 554
    },
    "minecraft:stone_stairs": {
        "id": 555
    },
    "minecraft:smooth_sandstone_stairs": {
        "id": 556
    },
    "minecraft:smooth_quartz_stairs": {
        "id": 557
    },
    "minecraft:granite_stairs": {
        "id": 558
    },
    "minecraft:andesite_stairs": {
        "id": 559
    },
    "minecraft:red_nether_brick_stairs": {
        "id": 560
    },
    "minecraft:polished_andesite_stairs": {
        "id": 561
    },
    "minecraft:diorite_stairs": {
        "id": 562
    },
    "minecraft:cobbled_deepslate_stairs": {
        "id": 563
    },
    "minecraft:polished_deepslate_stairs": {
        "id": 564
    },
    "minecraft:deepslate_brick_stairs": {
        "id": 565
    },
    "minecraft:deepslate_tile_stairs": {
        "id": 566
    },
    "minecraft:polished_granite_slab": {
        "id": 567
    },
    "minecraft:smooth_red_sandstone_slab": {
        "id": 568
    },
    "minecraft:mossy_stone_brick_slab": {
        "id": 569
    },
    "minecraft:polished_diorite_slab": {
        "id": 570
    },
    "minecraft:mossy_cobblestone_slab": {
        "id": 571
    },
    "minecraft:end_stone_brick_slab": {
        "id": 572
    },
    "minecraft:smooth_sandstone_slab": {
        "id": 573
    },
    "minecraft:smooth_quartz_slab": {
        "id": 574
    },
    "minecraft:granite_slab": {
        "id": 575
    },
    "minecraft:andesite_slab": {
        "id": 576
    },
    "minecraft:red_nether_brick_slab": {
        "id": 577
    },
    "minecraft:polished_andesite_slab": {
        "id": 578
    },
    "minecraft:diorite_slab": {
        "id": 579
    },
    "minecraft:cobbled_deepslate_slab": {
        "id": 580
    },
    "minecraft:polished_deepslate_slab": {
        "id": 581
    },
    "minecraft:deepslate_brick_slab": {
        "id": 582
    },
    "minecraft:deepslate_tile_slab": {
        "id": 583
    },
    "minecraft:scaffolding": {
        "id": 584
    },
    "minecraft:redstone": {
        "id": 585
    },
    "minecraft:redstone_torch": {
        "id": 586
    },
    "minecraft:redstone_block": {
        "id": 587
    },
    "minecraft:repeater": {
        "id": 588
    },
    "minecraft:comparator": {
        "id": 589
    },
    "minecraft:piston": {
        "id": 590
    },
    "minecraft:sticky_piston": {
        "id": 591
    },
    "minecraft:slime_block": {
        "id": 592
    },
    "minecraft:honey_block": {
        "id": 593
    },
    "minecraft:observer": {
        "id": 594
    },
    "minecraft:hopper": {
        "id": 595
    },
    "minecraft:dispenser": {
        "id": 596
    },
    "minecraft:dropper": {
        "id": 597
    },
    "minecraft:lectern": {
        "id": 598
    },
    "minecraft:target": {
        "id": 599
    },
    "minecraft:lever": {
        "id": 600
    },
    "minecraft:lightning_rod": {
        "id": 601
    },
    "minecraft:daylight_detector": {
        "id": 602
    },
    "minecraft:sculk_sensor": {
        "id": 603
    },
    "minecraft:tripwire_hook": {
        "id": 604
    },
    "minecraft:trapped_chest": {
        "id": 605
    },
    "minecraft:tnt": {
        "id": 606
    },
    "minecraft:redstone_lamp": {
        "id": 607
    },
    "minecraft:note_block": {
        "id": 608
    },
    "minecraft:stone_button": {
        "id": 609
    },
    "minecraft:polished_blackstone_button": {
        "id": 610
    },
    "minecraft:oak_button": {
        "id": 611
    },
    "minecraft:spruce_button": {
        "id": 612
    },
    "minecraft:birch_button": {
        "id": 613
    },
    "minecraft:jungle_button": {
        "id": 614
    },
    "minecraft:acacia_button": {
        "id": 615
    },
    "minecraft:dark_oak_button": {
        "id": 616
    },
    "minecraft:crimson_button": {
        "id": 617
    },
    "minecraft:warped_button": {
        "id": 618
    },
    "minecraft:stone_pressure_plate": {
        "id": 619
    },
    "minecraft:polished_blackstone_pressure_plate": {
        "id": 620
    },
    "minecraft:light_weighted_pressure_plate": {
        "id": 621
    },
    "minecraft:heavy_weighted_pressure_plate": {
        "id": 622
    },
    "minecraft:oak_pressure_plate": {
        "id": 623
    },
    "minecraft:spruce_pressure_plate": {
        "id": 624
    },
    "minecraft:birch_pressure_plate": {
        "id": 625
    },
    "minecraft:jungle_pressure_plate": {
        "id": 626
    },
    "minecraft:acacia_pressure_plate": {
        "id": 627
    },
    "minecraft:dark_oak_pressure_plate": {
        "id": 628
    },
    "minecraft:crimson_pressure_plate": {
        "id": 629
    },
    "minecraft:warped_pressure_plate": {
        "id": 630
    },
    "minecraft:iron_door": {
        "id": 631
    },
    "minecraft:oak_door": {
        "id": 632
    },
    "minecraft:spruce_door": {
        "id": 633
    },
    "minecraft:birch_door": {
        "id": 634
    },
    "minecraft:jungle_door": {
        "id": 635
    },
    "minecraft:acacia_door": {
        "id": 636
    },
    "minecraft:dark_oak_door": {
        "id": 637
    },
    "minecraft:crimson_door": {
        "id": 638
    },
    "minecraft:warped_door": {
        "id": 639
    },
    "minecraft:iron_trapdoor": {
        "id": 640
    },
    "minecraft:oak_trapdoor": {
        "id": 641
    },
    "minecraft:spruce_trapdoor": {
        "id": 642
    },
    "minecraft:birch_trapdoor": {
        "id": 643
    },
    "minecraft:jungle_trapdoor": {
        "id": 644
    },
    "minecraft:acacia_trapdoor": {
        "id": 645
    },
    "minecraft:dark_oak_trapdoor": {
        "id": 646
    },
    "minecraft:crimson_trapdoor": {
        "id": 647
    },
    "minecraft:warped_trapdoor": {
        "id": 648
    },
    "minecraft:oak_fence_gate": {
        "id": 649
    },
    "minecraft:spruce_fence_gate": {
        "id": 650
    },
    "minecraft:birch_fence_gate": {
        "id": 651
    },
    "minecraft:jungle_fence_gate": {
        "id": 652
    },
    "minecraft:acacia_fence_gate": {
        "id": 653
    },
    "minecraft:dark_oak_fence_gate": {
        "id": 654
    },
    "minecraft:crimson_fence_gate": {
        "id": 655
    },
    "minecraft:warped_fence_gate": {
        "id": 656
    },
    "minecraft:powered_rail": {
        "id": 657
    },
    "minecraft:detector_rail": {
        "id": 658
    },
    "minecraft:rail": {
        "id": 659
    },
    "minecraft:activator_rail": {
        "id": 660
    },
    "minecraft:saddle": {
        "id": 661,
        "stack_size": 1
    },
    "minecraft:minecart": {
        "id": 662,
        "stack_size": 1
    },
    "minecraft:chest_minecart": {
        "id": 663,
        "stack_size": 1
    },
    "minecraft:furnace_minecart": {
        "id": 664,
        "stack_size": 1
    },
    "minecraft:tnt_minecart": {
        "id": 665,
        "stack_size": 1
    },
    "minecraft:hopper_minecart": {
        "id": 666,
        "stack_size": 1
    },
    "minecraft:carrot_on_a_stick": {
        "id": 667,
        "stack_size": 1,
        "durability": 25
    },
    "minecraft:warped_fungus_on_a_stick": {
        "id": 668,
        "stack_size": 1,
        "durability": 100
    },
    "minecraft:elytra": {
        "id": 669,
        "stack_size": 1,
        "durability": 432
    },
    "minecraft:oak_boat": {
        "id": 670,
        "stack_size": 1
    },
    "minecraft:spruce_boat": {
        "id": 671,
        "stack_size": 1
    },
    "minecraft:birch_boat": {
        "id": 672,
        "stack_size": 1
    },
    "minecraft:jungle_boat": {
        "id": 673,
        "stack_size": 1
    },
    "minecraft:acacia_boat": {
        "id": 674,
        "stack_size": 1
    },
    "minecraft:dark_oak_boat": {
        "id": 675,
        "stack_size": 1
    },
    "minecraft:structure_block": {
        "id": 676
    },
    "minecraft:jigsaw": {
        "id": 677
    },
    "minecraft:turtle_helmet": {
        "id": 678,
        "stack_size": 1,
        "durability": 275
    },
    "minecraft:scute": {
        "id": 679
    },
    "minecraft:flint_and_steel": {
        "id": 680,
        "stack_size": 1,
        "durability": 64
    },
    "minecraft:apple": {
        "id": 681
    },
    "minecraft:bow": {
        "id": 682,
        "stack_size": 1,
        "durability": 384
    },
    "minecraft:arrow": {
        "id": 683
    },
    "minecraft:coal": {
        "id": 684
    },
    "minecraft:charcoal": {
        "id": 685
    },
    "minecraft:diamond": {
        "id": 686
    },
    "minecraft:emerald": {
        "id": 687
    },
    "minecraft:lapis_lazuli": {
        "id": 688
    },
    "minecraft:quartz": {
        "id": 689
    },
    "minecraft:amethyst_shard": {
        "id": 690
    },
    "minecraft:raw_iron": {
        "id": 691
    },
    "minecraft:iron_ingot": {
        "id": 692
    },
    "minecraft:raw_copper": {
        "id": 693
    },
    "minecraft:copper_ingot": {
        "id": 694
    },
    "minecraft:raw_gold": {
        "id": 695
    },
    "minecraft:gold_ingot": {
        "id": 696
    },
    "minecraft:netherite_ingot": {
        "id": 697
    },
    "minecraft:netherite_scrap": {
        "id": 698
    },
    "minecraft:wooden_sword": {
        "id": 699,
        "stack_size": 1,
        "durability": 59
    },
    "minecraft:wooden_shovel": {
        "id": 700,
        "stack_size": 1,
        "durability": 59
    },
    "minecraft:wooden_pickaxe": {
        "id": 701,
        "stack_size": 1,
        "durability": 59
    },
    "minecraft:wooden_axe": {
        "id": 702,
        "stack_size": 1,
        "durability": 59
    },
    "minecraft:wooden_hoe": {
        "id": 703,
        "stack_size": 1,
        "durability": 59
    },
    "minecraft:stone_sword": {
        "id": 704,
        "stack_size": 1,
        "durability": 131
    },
    "minecraft:stone_shovel": {
        "id": 705,
        "stack_size": 1,
        "durability": 131
    },
    "minecraft:stone_pickaxe": {
        "id": 706,
        "stack_size": 1,
        "durability": 131
    },
    "minecraft:stone_axe": {
        "id": 707,
        "stack_size": 1,
        "durability": 131
    },
    "minecraft:stone_hoe": {
        "id": 708,
        "stack_size": 1,
        "durability": 131
    },
    "minecraft:golden_sword": {
        "id": 709,
        "stack_size": 1,
        "durability": 32
    },
    "minecraft:golden_shovel": {
        "id": 710,
        "stack_size": 1,
        "durability": 32
    },
    "minecraft:golden_pickaxe": {
        "id": 711,
        "stack_size": 1,
        "durability": 32
    },
    "minecraft:golden_axe": {
        "id": 712,
        "stack_size": 1,
        "durability": 32
    },
    "minecraft:golden_hoe": {
        "id": 713,
        "stack_size": 1,
        "durability": 32
    },
    "minecraft:iron_sword": {
        "id": 714,
        "stack_size": 1,
        "durability": 250
    },
    "minecraft:iron_shovel": {
        "id": 715,
        "stack_size": 1,
        "durability": 250
    },
    "minecraft:iron_pickaxe": {
        "id": 716,
        "stack_size": 1,
        "durability": 250
    },
    "minecraft:iron_axe": {
        "id": 717,
        "stack_size": 1,
        "durability": 250
    },
    "minecraft:iron_hoe": {
        "id": 718,
        "stack_size": 1,
        "durability": 250
    },
    "minecraft:diamond_sword": {
        "id": 719,
        "stack_size": 1,
        "durability": 1561
    },
    "minecraft:diamond_shovel": {
        "id": 720,
        "stack_size": 1,
        "durability": 1561
    },
    "minecraft:diamond_pickaxe": {
        "id": 721,
        "stack_size": 1,
        "durability": 1561
    },
    "minecraft:diamond_axe": {
        "id": 722,
        "stack_size": 1,
        "durability": 1561
    },
    "minecraft:diamond_hoe": {
        "id": 723,
        "stack_size": 1,
        "durability": 1561
    },
    "minecraft:netherite_sword": {
        "id": 724,
        "stack_size": 1,
        "durability": 2031
    },
    "minecraft:netherite_shovel": {
        "id": 725,
        "stack_size": 1,
        "durability": 2031
    },
    "minecraft:netherite_pickaxe": {
        "id": 726,
        "stack_size": 1,
        "durability": 2031
    },
    "minecraft:netherite_axe": {
        "id": 727,
        "stack_size": 1,
        "durability": 2031
    },
    "minecraft:netherite_hoe": {
        "id": 728,
        "stack_size": 1,
        "durability": 2031
    },
    "minecraft:stick": {
        "id": 729
    },
    "minecraft:bowl": {
        "id": 730
    },
    "minecraft:mushroom_stew": {
        "id": 731,
        "stack_size": 1
    },
    "minecraft:string": {
        "id": 732
    },
    "minecraft:feather": {
        "id": 733
    },
    "minecraft:gunpowder": {
        "id": 734
    },
    "minecraft:wheat_seeds": {
        "id": 735
    },
    "minecraft:wheat": {
        "id": 736
    },
    "minecraft:bread": {
        "id": 737
    },
    "minecraft:leather_helmet": {
        "id": 738,
        "stack_size": 1,
        "durability": 55
    },
    "minecraft:leather_chestplate": {
        "id": 739,
        "stack_size": 1,
        "durability": 80
    },
    "minecraft:leather_leggings": {
        "id": 740,
        "stack_size": 1,
        "durability": 75
    },
    "minecraft:leather_boots": {
        "id": 741,
        "stack_size": 1,
        "durability": 65
    },
    "minecraft:chainmail_helmet": {
        "id": 742,
        "stack_size": 1,
        "durability": 165
    },
    "minecraft:chainmail_chestplate": {
        "id": 743,
        "stack_size": 1,
        "durability": 240
    },
    "minecraft:chainmail_leggings": {
        "id": 744,
        "stack_size": 1,
        "durability": 225
    },
    "minecraft:chainmail_boots": {
        "id": 745,
        "stack_size": 1,
        "durability": 195
    },
    "minecraft:iron_helmet": {
        "id": 746,
        "stack_size": 1,
        "durability": 165
    },
    "minecraft:iron_chestplate": {
        "id": 747,
        "stack_size": 1,
        "durability": 240
    },
    "minecraft:iron_leggings": {
        "id": 748,
        "stack_size": 1,
        "durability": 225
    },
    "minecraft:iron_boots": {
        "id": 749,
        "stack_size": 1,
        "durability": 195
    },
    "minecraft:diamond_helmet": {
        "id": 750,
        "stack_size": 1,
        "durability": 363
    },
    "minecraft:diamond_chestplate": {
        "id": 751,
        "stack_size": 1,
        "durability": 528
    },
    "minecraft:diamond_leggings": {
        "id": 752,
        "stack_size": 1,
        "durability": 495
    },
    "minecraft:diamond_boots": {
        "id": 753,
        "stack_size": 1,
        "durability": 429
    },
    "minecraft:golden_helmet": {
        "id": 754,
        "stack_size": 1,
        "durability": 77
    },
    "minecraft:golden_chestplate": {
        "id": 755,
        "stack_size": 1,
        "durability": 112
    },
    "minecraft:golden_leggings": {
        "id": 756,
        "stack_size": 1,
        "durability": 105
    },
    "minecraft:golden_boots": {
        "id": 757,
        "stack_size": 1,
        "durability": 91
    },
    "minecraft:netherite_helmet": {
        "id": 758,
        "stack_size": 1,
        "durability": 407
    },
    "minecraft:netherite_chestplate": {
        "id": 759,
        "stack_size": 1,
        "durability": 592
    },
    "minecraft:netherite_leggings": {
        "id": 760,
        "stack_size": 1,
        "durability": 555
    },
    "minecraft:netherite_boots": {
        "id": 761,
        "stack_size": 1,
        "durability": 481
    },
    "minecraft:flint": {
        "id": 762
    },
    "minecraft:porkchop": {
        "id": 763
    },
    "minecraft:cooked_porkchop": {
        "id": 764
    },
    "minecraft:painting": {
        "id": 765
    },
    "minecraft:golden_apple": {
        "id": 766
    },
    "minecraft:enchanted_golden_apple": {
        "id": 767
    },
    "minecraft:oak_sign": {
        "id": 768,
        "stack_size": 16
    },
    "minecraft:spruce_sign": {
        "id": 769,
        "stack_size": 16
    },
    "minecraft:birch_sign": {
        "id": 770,
        "stack_size": 16
    },
    "minecraft:jungle_sign": {
        "id": 771,
        "stack_size": 16
    },
    "minecraft:acacia_sign": {
        "id": 772,
        "stack_size": 16
    },
    "minecraft:dark_oak_sign": {
        "id": 773,
        "stack_size": 16
    },
    "minecraft:crimson_sign": {
        "id": 774,
        "stack_size": 16
    },
    "minecraft:warped_sign": {
        "id": 775,
        "stack_size": 16
    },
    "minecraft:bucket": {
        "id": 776,
        "stack_size": 16
    },
    "minecraft:water_bucket": {
        "id": 777,
        "stack_size": 1
    },
    "minecraft:lava_bucket": {
        "id": 778,
        "stack_size": 1
    },
    "minecraft:powder_snow_bucket": {
        "id": 779,
        "stack_size": 1
    },
    "minecraft:snowball": {
        "id": 780,
        "stack_size": 16
    },
    "minecraft:leather": {
        "id": 781
    },
    "minecraft:milk_bucket": {
        "id": 782,
        "stack_size": 1
    },
    "minecraft:pufferfish_bucket": {
        "id": 783,
        "stack_size": 1
    },
    "minecraft:salmon_bucket": {
        "id": 784,
        "stack_size": 1
    },
    "minecraft:cod_bucket": {
        "id": 785,
        "stack_size": 1
    },
    "minecraft:tropical_fish_bucket": {
        "id": 786,
        "stack_size": 1
    },
    "minecraft:axolotl_bucket": {
        "id": 787,
        "stack_size": 1
    },
    "minecraft:brick": {
        "id": 788
    },
    "minecraft:clay_ball": {
        "id": 789
    },
    "minecraft:dried_kelp_block": {
        "id": 790
    },
    "minecraft:paper": {
        "id": 791
    },
    "minecraft:book": {
        "id": 792
    },
    "minecraft:slime_ball": {
        "id": 793
    },
    "minecraft:egg": {
        "id": 794,
        "stack_size": 16
    },
    "minecraft:compass": {
        "id": 795
    },
    "minecraft:bundle": {
        "id": 796,
        "stack_size": 1
    },
    "minecraft:fishing_rod": {
        "id": 797,
        "stack_size": 1,
        "durability": 64
    },
    "minecraft:clock": {
        "id": 798
    },
    "minecraft:spyglass": {
        "id": 799,
        "stack_size": 1
    },
    "minecraft:glowstone_dust": {
        "id": 800
    },
    "minecraft:cod": {
        "id": 801
    },
    "minecraft:salmon": {
        "id": 802
    },
    "minecraft:tropical_fish": {
        "id": 803
    },
    "minecraft:pufferfish": {
        "id": 804
    },
    "minecraft:cooked_cod": {
        "id": 805
    },
    "minecraft:cooked_salmon": {
        "id": 806
    },
    "minecraft:ink_sac": {
        "id": 807
    },
    "minecraft:glow_ink_sac": {
        "id": 808
    },
    "minecraft:cocoa_beans": {
        "id": 809
    },
    "minecraft:white_dye": {
        "id": 810
    },
    "minecraft:orange_dye": {
        "id": 811
    },
    "minecraft:magenta_dye": {
        "id": 812
    },
    "minecraft:light_blue_dye": {
        "id": 813
    },
    "minecraft:yellow_dye": {
        "id": 814
    },
    "minecraft:lime_dye": {
        "id": 815
    },
    "minecraft:pink_dye": {
        "id": 816
    },
    "minecraft:gray_dye": {
        "id": 817
    },
    "minecraft:light_gray_dye": {
        "id": 818
    },
    "minecraft:cyan_dye": {
        "id": 819
    },
    "minecraft:purple_dye": {
        "id": 820
    },
    "minecraft:blue_dye": {
        "id": 821
    },
    "minecraft:brown_dye": {
        "id": 822
    },
    "minecraft:green_dye": {
        "id": 823
    },
    "minecraft:red_dye": {
        "id": 824
    },
    "minecraft:black_dye": {
        "id": 825
    },
    "minecraft:bone_meal": {
        "id": 826
    },
    "minecraft:bone": {
        "id": 827
    },
    "minecraft:sugar": {
        "id": 828
    },
    "minecraft:cake": {
        "id": 829,
        "stack_size": 1
    },
    "minecraft:white_bed": {
        "id": 830,
        "stack_size": 1
    },
    "minecraft:orange_bed": {
        "id": 831,
        "stack_size": 1
    },
    "minecraft:magenta_bed": {
        "id": 832,
        "stack_size": 1
    },
    "minecraft:light_blue_bed": {
        "id": 833,
        "stack_size": 1
    },
    "minecraft:yellow_bed": {
        "id": 834,
        "stack_size": 1
    },
    "minecraft:lime_bed": {
        "id": 835,
        "stack_size": 1
    },
    "minecraft:pink_bed": {
        "id": 836,
        "stack_size": 1
    },
    "minecraft:gray_bed": {
        "id": 837,
        "stack_size": 1
    },
    "minecraft:light_gray_bed": {
        "id": 838,
        "stack_size": 1
    },
    "minecraft:cyan_bed": {
        "id": 839,
        "stack_size": 1
    },
    "minecraft:purple_bed": {
        "id": 840,
        "stack_size": 1
    },
    "minecraft:blue_bed": {
        "id": 841,
        "stack_size": 1
    },
    "minecraft:brown_bed": {
        "id": 842,
        "stack_size": 1
    },
    "minecraft:green_bed": {
        "id": 843,
        "stack_size": 1
    },
    "minecraft:red_bed": {
        "id": 844,
        "stack_size": 1
    },
    "minecraft:black_bed": {
        "id": 845,
        "stack_size": 1
    },
    "minecraft:cookie": {
        "id": 846
    },
    "minecraft:filled_map": {
        "id": 847
    },
    "minecraft:shears": {
        "id": 848,
        "stack_size": 1,
        "durability": 238
    },
    "minecraft:melon_slice": {
        "id": 849
    },
    "minecraft:dried_kelp": {
        "id": 850
    },
    "minecraft:pumpkin_seeds": {
        "id": 851
    },
    "minecraft:melon_seeds": {
        "id": 852
    },
    "minecraft:beef": {
        "id": 853
    },
    "minecraft:cooked_beef": {
        "id": 854
    },
    "minecraft:chicken": {
        "id": 855
    },
    "minecraft:cooked_chicken": {
        "id": 856
    },
    "minecraft:rotten_flesh": {
        "id": 857
    },
    "minecraft:ender_pearl": {
        "id": 858,
        "stack_size": 16
    },
    "minecraft:blaze_rod": {
        "id": 859
    },
    "minecraft:ghast_tear": {
        "id": 860
    },
    "minecraft:gold_nugget": {
        "id": 861
    },
    "minecraft:nether_wart": {
        "id": 862
    },
    "minecraft:potion": {
        "id": 863,
        "stack_size": 1
    },
    "minecraft:glass_bottle": {
        "id": 864
    },
    "minecraft:spider_eye": {
        "id": 865
    },
    "minecraft:fermented_spider_eye": {
        "id": 866
    },
    "minecraft:blaze_powder": {
        "id": 867
    },
    "minecraft:magma_cream": {
        "id": 868
    },
    "minecraft:brewing_stand": {
        "id": 869
    },
    "minecraft:cauldron": {
        "id": 870
    },
    "minecraft:ender_eye": {
        "id": 871
    },
    "minecraft:glistering_melon_slice": {
        "id": 872
    },
    "minecraft:axolotl_spawn_egg": {
        "id": 873
    },
    "minecraft:bat_spawn_egg": {
        "id": 874
    },
    "minecraft:bee_spawn_egg": {
        "id": 875
    },
    "minecraft:blaze_spawn_egg": {
        "id": 876
    },
    "minecraft:cat_spawn_egg": {
        "id": 877
    },
    "minecraft:cave_spider_spawn_egg": {
        "id": 878
    },
    "minecraft:chicken_spawn_egg": {
        "id": 879
    },
    "minecraft:cod_spawn_egg": {
        "id": 880
    },
    "minecraft:cow_spawn_egg": {
        "id": 881
    },
    "minecraft:creeper_spawn_egg": {
        "id": 882
    },
    "minecraft:dolphin_spawn_egg": {
        "id": 883
    },
    "minecraft:donkey_spawn_egg": {
        "id": 884
    },
    "minecraft:drowned_spawn_egg": {
        "id": 885
    },
    "minecraft:elder_guardian_spawn_egg": {
        "id": 886
    },
    "minecraft:enderman_spawn_egg": {
        "id": 887
    },
    "minecraft:endermite_spawn_egg": {
        "id": 888
    },
    "minecraft:evoker_spawn_egg": {
        "id": 889
    },
    "minecraft:fox_spawn_egg": {
        "id": 890
    },
    "minecraft:ghast_spawn_egg": {
        "id": 891
    },
    "minecraft:glow_squid_spawn_egg": {
        "id": 892
    },
    "minecraft:goat_spawn_egg": {
        "id": 893
    },
    "minecraft:guardian_spawn_egg": {
        "id": 894
    },
    "minecraft:hoglin_spawn_egg": {
        "id": 895
    },
    "minecraft:horse_spawn_egg": {
        "id": 896
    },
    "minecraft:husk_spawn_egg": {
        "id": 897
    },
    "minecraft:llama_spawn_egg": {
        "id": 898
    },
    "minecraft:magma_cube_spawn_egg": {
        "id": 899
    },
    "minecraft:mooshroom_spawn_egg": {
        "id": 900
    },
    "minecraft:mule_spawn_egg": {
        "id": 901
    },
    "minecraft:ocelot_spawn_egg": {
        "id": 902
    },
    "minecraft:panda_spawn_egg": {
        "id": 903
    },
    "minecraft:parrot_spawn_egg": {
        "id": 904
    },
    "minecraft:phantom_spawn_egg": {
        "id": 905
    },
    "minecraft:pig_spawn_egg": {
        "id": 906
    },
    "minecraft:piglin_spawn_egg": {
        "id": 907
    },
    "minecraft:piglin_brute_spawn_egg": {
        "id": 908
    },
    "minecraft:pillager_spawn_egg": {
        "id": 909
    },
    "minecraft:polar_bear_spawn_egg": {
        "id": 910
    },
    "minecraft:pufferfish_spawn_egg": {
        "id": 911
    },
    "minecraft:rabbit_spawn_egg": {
        "id": 912
    },
    "minecraft:ravager_spawn_egg": {
        "id": 913
    },
    "minecraft:salmon_spawn_egg": {
        "id": 914
    },
    "minecraft:sheep_spawn_egg": {
        "id": 915
    },
    "minecraft:shulker_spawn_egg": {
        "id": 916
    },
    "minecraft:silverfish_spawn_egg": {
        "id": 917
    },
    "minecraft:skeleton_spawn_egg": {
        "id": 918
    },
    "minecraft:skeleton_horse_spawn_egg": {
        "id": 919
    },
    "minecraft:slime_spawn_egg": {
        "id": 920
    },
    "minecraft:spider_spawn_egg": {
        "id": 921
    },
    "minecraft:squid_spawn_egg": {
        "id": 922
    },
    "minecraft:stray_spawn_egg": {
        "id": 923
    },
    "minecraft:strider_spawn_egg": {
        "id": 924
    },
    "minecraft:trader_llama_spawn_egg": {
        "id": 925
    },
    "minecraft:tropical_fish_spawn_egg": {
        "id": 926
    },
    "minecraft:turtle_spawn_egg": {
        "id": 927
    },
    "minecraft:vex_spawn_egg": {
        "id": 928
    },
    "minecraft:villager_spawn_egg": {
        "id": 929
    },
    "minecraft:vindicator_spawn_egg": {
        "id": 930
    },
    "minecraft:wandering_trader_spawn_egg": {
        "id": 931
    },
    "minecraft:witch_spawn_egg": {
        "id": 932
    },
    "minecraft:wither_skeleton_spawn_egg": {
        "id": 933
    },
    "minecraft:wolf_spawn_egg": {
        "id": 934
    },
    "minecraft:zoglin_spawn_egg": {
        "id": 935
    },
    "minecraft:zombie_spawn_egg": {
        "id": 936
    },
    "minecraft:zombie_horse_spawn_egg": {
        "id": 937
    },
    "minecraft:zombie_villager_spawn_egg": {
        "id": 938
    },
    "minecraft:zombified_piglin_spawn_egg": {
        "id": 939
    },
    "minecraft:experience_bottle": {
        "id": 940
    },
    "minecraft:fire_charge": {
        "id": 941
    },
    "minecraft:writable_book": {
        "id": 942,
        "stack_size": 1
    },
    "minecraft:written_book": {
        "id": 943,
        "stack_size": 16
    },
    "minecraft:item_frame": {
        "id": 944
    },
    "minecraft:glow_item_frame": {
        "id": 945
    },
    "minecraft:flower_pot": {
        "id": 946
    },
    "minecraft:carrot": {
        "id": 947
    },
    "minecraft:potato": {
        "id": 948
    },
    "minecraft:baked_potato": {
        "id": 949
    },
    "minecraft:poisonous_potato": {
        "id": 950
    },
    "minecraft:map": {
        "id": 951
    },
    "minecraft:golden_carrot": {
        "id": 952
    },
    "minecraft:skeleton_skull": {
        "id": 953
    },
    "minecraft:wither_skeleton_skull": {
        "id": 954
    },
    "minecraft:player_head": {
        "id": 955
    },
    "minecraft:zombie_head": {
        "id": 956
    },
    "minecraft:creeper_head": {
        "id": 957
    },
    "minecraft:dragon_head": {
        "id": 958
    },
    "minecraft:nether_star": {
        "id": 959
    },
    "minecraft:pumpkin_pie": {
        "id": 960
    },
    "minecraft:firework_rocket": {
        "id": 961
    },
    "minecraft:firework_star": {
        "id": 962
    },
    "minecraft:enchanted_book": {
        "id": 963,
        "stack_size": 1
    },
    "minecraft:nether_brick": {
        "id": 964
    },
    "minecraft:prismarine_shard": {
        "id": 965
    },
    "minecraft:prismarine_crystals": {
        "id": 966
    },
    "minecraft:rabbit": {
        "id": 967
    },
    "minecraft:cooked_rabbit": {
        "id": 968
    },
    "minecraft:rabbit_stew": {
        "id": 969,
        "stack_size": 1
    },
    "minecraft:rabbit_foot": {
        "id": 970
    },
    "minecraft:rabbit_hide": {
        "id": 971
    },
    "minecraft:armor_stand": {
        "id": 972,
        "stack_size": 16
    },
    "minecraft:iron_horse_armor": {
        "id": 973,
        "stack_size": 1
    },
    "minecraft:golden_horse_armor": {
        "id": 974,
        "stack_size": 1
    },
    "minecraft:diamond_horse_armor": {
        "id": 975,
        "stack_size": 1
    },
    "minecraft:leather_horse_armor": {
        "id": 976,
        "stack_size": 1
    },
    "minecraft:lead": {
        "id": 977
    },
    "minecraft:name_tag": {
        "id": 978
    },
    "minecraft:command_block_minecart": {
        "id": 979,
        "stack_size": 1
    },
    "minecraft:mutton": {
        "id": 980
    },
    "minecraft:cooked_mutton": {
        "id": 981
    },
    "minecraft:white_banner": {
        "id": 982,
        "stack_size": 16
    },
    "minecraft:orange_banner": {
        "id": 983,
        "stack_size": 16
    },
    "minecraft:magenta_banner": {
        "id": 984,
        "stack_size": 16
    },
    "minecraft:light_blue_banner": {
        "id": 985,
        "stack_size": 16
    },
    "minecraft:yellow_banner": {
        "id": 986,
        "stack_size": 16
    },
    "minecraft:lime_banner": {
        "id": 987,
        "stack_size": 16
    },
    "minecraft:pink_banner": {
        "id": 988,
        "stack_size": 16
    },
    "minecraft:gray_banner": {
        "id": 989,
        "stack_size": 16
    },
    "minecraft:light_gray_banner": {
        "id": 990,
        "stack_size": 16
    },
    "minecraft:cyan_banner": {
        "id": 991,
        "stack_size": 16
    },
    "minecraft:purple_banner": {
        "id": 992,
        "stack_size": 16
    },
    "minecraft:blue_banner": {
        "id": 993,
        "stack_size": 16
    },
    "minecraft:brown_banner": {
        "id": 994,
        "stack_size": 16
    },
    "minecraft:green_banner": {
        "id": 995,
        "stack_size": 16
    },
    "minecraft:red_banner": {
        "id": 996,
        "stack_size": 16
    },
    "minecraft:black_banner": {
        "id": 997,
        "stack_size": 16
    },
    "minecraft:end_crystal": {
        "id": 998
    },
    "minecraft:chorus_fruit": {
        "id": 999
    },
    "minecraft:popped_chorus_fruit": {
        "id": 1000
    },
    "minecraft:beetroot": {
        "id": 1001
    },
    "minecraft:beetroot_seeds": {
        "id": 1002
    },
    "minecraft:beetroot_soup": {
        "id": 1003,
        "stack_size": 1
    },
    "minecraft:dragon_breath": {
        "id": 1004
    },
    "minecraft:splash_potion": {
        "id": 1005,
        "stack_size": 1
    },
    "minecraft:spectral_arrow": {
        "id": 1006
    },
    "minecraft:tipped_arrow": {
        "id": 1007
    },
    "minecraft:lingering_potion": {
        "id": 1008,
        "stack_size": 1
    },
    "minecraft:shield": {
        "id": 1009,
        "stack_size": 1,
        "durability": 336
    },
    "minecraft:totem_of_undying": {
        "id": 1010,
        "stack_size": 1
    },
    "minecraft:shulker_shell": {
        "id": 1011
    },
    "minecraft:iron_nugget": {
        "id": 1012
    },
    "minecraft:knowledge_book": {
        "id": 1013,
        "stack_size": 1
    },
    "minecraft:debug_stick": {
        "id": 1014,
        "stack_size": 1
    },
    "minecraft:music_disc_13": {
        "id": 1015,
        "stack_size": 1
    },
    "minecraft:music_disc_cat": {
        "id": 1016,
        "stack_size": 1
    },
    "minecraft:music_disc_blocks": {
        "id": 1017,
        "stack_size": 1
    },
    "minecraft:music_disc_chirp": {
        "id": 1018,
        "stack_size": 1
    },
    "minecraft:music_disc_far": {
        "id": 1019,
        "stack_size": 1
    },
    "minecraft:music_disc_mall": {
        "id": 1020,
        "stack_size": 1
    },
    "minecraft:music_disc_mellohi": {
        "id": 1021,
        "stack_size": 1
    },
    "minecraft:music_disc_stal": {
        "id": 1022,
        "stack_size": 1
    },
    "minecraft:music_disc_strad": {
        "id": 1023,
        "stack_size": 1
    },
    "minecraft:music_disc_ward": {
        "id": 1024,
        "stack_size": 1
    },
    "minecraft:music_disc_11": {
        "id": 1025,
        "stack_size": 1
    },
    "minecraft:music_disc_wait": {
        "id": 1026,
        "stack_size": 1
    },
    "minecraft:music_disc_pigstep": {
        "id": 1027,
        "stack_size": 1
    },
    "minecraft:trident": {
        "id": 1028,
        "stack_size": 1,
        "durability": 250
    },
    "minecraft:phantom_membrane": {
        "id": 1029
    },
    "minecraft:nautilus_shell": {
        "id": 1030
    },
    "minecraft:heart_of_the_sea": {
        "id": 1031
    },
    "minecraft:crossbow": {
        "id": 1032,
        "stack_size": 1,
        "durability": 465
    },
    "minecraft:suspicious_stew": {
        "id": 1033,
        "stack_size": 1
    },
    "minecraft:loom": {
        "id": 1034
    },
    "minecraft:flower_banner_pattern": {
        "id": 1035,
        "stack_size": 1
    },
    "minecraft:creeper_banner_pattern": {
        "id": 1036,
        "stack_size": 1
    },
    "minecraft:skull_banner_pattern": {
        "id": 1037,
        "stack_size": 1
    },
    "minecraft:mojang_banner_pattern": {
        "id": 1038,
        "stack_size": 1
    },
    "minecraft:globe_banner_pattern": {
        "id": 1039,
        "stack_size": 1
    },
    "minecraft:piglin_banner_pattern": {
        "id": 1040,
        "stack_size": 1
    },
    "minecraft:composter": {
        "id": 1041
    },
    "minecraft:barrel": {
        "id": 1042
    },
    "minecraft:smoker": {
        "id": 1043
    },
    "minecraft:blast_furnace": {
        "id": 1044
    },
    "minecraft:cartography_table": {
        "id": 1045
    },
    "minecraft:fletching_table": {
        "id": 1046
    },
    "minecraft:grindstone": {
        "id": 1047
    },
    "minecraft:smithing_table": {
        "id": 1048
    },
    "minecraft:stonecutter": {
        "id": 1049
    },
    "minecraft:bell": {
        "id": 1050
    },
    "minecraft:lantern": {
        "id": 1051
    },
    "minecraft:soul_lantern": {
        "id": 1052
    },
    "minecraft:sweet_berries": {
        "id": 1053
    },
    "minecraft:glow_berries": {
        "id": 1054
    },
    "minecraft:campfire": {
        "id": 1055
    },
    "minecraft:soul_campfire": {
        "id": 1056
    },
    "minecraft:shroomlight": {
        "id": 1057
    },
    "minecraft:honeycomb": {
        "id": 1058
    },
    "minecraft:bee_nest": {
        "id": 1059
    },
    "minecraft:beehive": {
        "id": 1060
    },
    "minecraft:honey_bottle": {
        "id": 1061,
        "stack_size": 16
    },
    "minecraft:honeycomb_block": {
        "id": 1062
    },
    "minecraft:lodestone": {
        "id": 1063
    },
    "minecraft:crying_obsidian": {
        "id": 1064
    },
    "minecraft:blackstone": {
        "id": 1065
    },
    "minecraft:blackstone_slab": {
        "id": 1066
    },
    "minecraft:blackstone_stairs": {
        "id": 1067
    },
    "minecraft:gilded_blackstone": {
        "id": 1068
    },
    "minecraft:polished_blackstone": {
        "id": 1069
    },
    "minecraft:polished_blackstone_slab": {
        "id": 1070
    },
    "minecraft:polished_blackstone_stairs": {
        "id": 1071
    },
    "minecraft:chiseled_polished_blackstone": {
        "id": 1072
    },
    "minecraft:polished_blackstone_bricks": {
        "id": 1073
    },
    "minecraft:polished_blackstone_brick_slab": {
        "id": 1074
    },
    "minecraft:polished_blackstone_brick_stairs": {
        "id": 1075
    },
    "minecraft:cracked_polished_blackstone_bricks": {
        "id": 1076
    },
    "minecraft:respawn_anchor": {
        "id": 1077
    },
    "minecraft:candle": {
        "id": 1078
    },
    "minecraft:white_candle": {
        "id": 1079
    },
    "minecraft:orange_candle": {
        "id": 1080
    },
    "minecraft:magenta_candle": {
        "id": 1081
    },
    "minecraft:light_blue_candle": {
        "id": 1082
    },
    "minecraft:yellow_candle": {
        "id": 1083
    },
    "minecraft:lime_candle": {
        "id": 1084
    },
    "minecraft:pink_candle": {
        "id": 1085
    },
    "minecraft:gray_candle": {
        "id": 1086
    },
    "minecraft:light_gray_candle": {
        "id": 1087
    },
    "minecraft:cyan_candle": {
        "id": 1088
    },
    "minecraft:purple_candle": {
        "id": 1089
    },
    "minecraft:blue_candle": {
        "id": 1090
    },
    "minecraft:brown_candle": {
        "id": 1091
    },
    "minecraft:green_candle": {
        "id": 1092
    },
    "minecraft:red_candle": {
        "id": 1093
    },
    "minecraft:black_candle": {
        "id": 1094
    },
    "minecraft:small_amethyst_bud": {
        "id": 1095
    },
    "minecraft:medium_amethyst_bud": {
        "id": 1096
    },
    "minecraft:large_amethyst_bud": {
        "id": 1097
    },
    "minecraft:amethyst_cluster": {
        "id": 1098
    },
    "minecraft:pointed_dripstone": {
        "id": 1099
    }
}