{
	"textures": {
		"all": "#all"
	},
	"elements": [
		{
			"__comment": "Head",
			"from": [4, 0, 4],
			"to": [12, 8, 12],
			"faces": {
				"down":  { "uv": [ 16, 0, 24, 8 ], "texture": "#all", "cullface": "down" },
                "up":    { "uv": [ 8, 0, 16, 8 ], "texture": "#all" },
                "south": { "uv": [ 24, 8, 32, 16 ], "texture": "#all" },
                "west":  { "uv": [ 16, 8, 24, 16 ], "texture": "#all" },
                "north":  { "uv": [ 8, 8, 16, 16 ], "texture": "#all" },
                "east":  { "uv": [ 0, 8, 8, 16 ], "texture": "#all" }
			}
		}
	]
}